{
    "name": "Customer Service",
    "type": "messaging",
    "language": "eng",
    "uuid": "9ecc8e84-6b83-442b-a04a-8094d5de997b",
    "localization": {
        "spa": {
            "360a28a1-6741-4f16-9421-f6f313cf753e": {
                "text": ["Hola, como te llamas?"]
            }
        }
    },
    "nodes": [
        {
            "uuid": "24afc61e-e528-4ac0-b887-78cebd39f12b",
            "actions": [
                {
                    "uuid": "360a28a1-6741-4f16-9421-f6f313cf753e",
                    "type": "send_msg",
                    "text": "Hi there, what is your name?"
                },
                {
                    "uuid": "d5293394-c6d4-407c-97da-8149faea24cf",
                    "type": "add_contact_groups",
                    "groups": [
                        {
                            "uuid": "2429d573-80d7-47f8-879f-f2ba442a1bfd",
                            "name": "Unsatisfied Customers"
                        },
                        {
                            "uuid": "783a5393-c47d-4dd0-bcfb-9ba8081d2f3f",
                            "name": "Unknown Group"
                        }
                    ]
                }
            ],
            "exits": [
                {
                    "name": null,
                    "uuid": "445fc64c-2a18-47cc-89d0-15172826bfcc",
                    "destination_uuid": "d642b014-3c91-418f-ad5b-0fb4f8c5ee60"
                }
            ]
        }
    ],
    "_ui": {
        "languages": [
            {
                "eng": "English"
            },
            {
                "spa": "Spanish"
            }
        ],
        "nodes": {
            "24afc61e-e528-4ac0-b887-78cebd39f12b": {
                "type": "execute_actions",
                "position": {
                    "left": 0,
                    "top": 0
                }
            }
        }
    }
}
